examples/config.py
gekim/__init__.py
gekim/fields/__init__.py
gekim/fields/bio/__init__.py
gekim/fields/bio/binding.py
gekim/fields/bio/cellular.py
gekim/fields/bio/folding.py
gekim/fields/bio/pharmaco.py
gekim/fields/bio/population.py
gekim/fields/bio/enzyme/__init__.py
gekim/fields/bio/enzyme/catalysis.py
gekim/fields/bio/enzyme/inhib/__init__.py
gekim/fields/bio/enzyme/inhib/irrev.py
gekim/fields/bio/enzyme/inhib/rev.py
gekim/fields/chem/__init__.py
gekim/fields/chem/atmospheric.py
gekim/fields/chem/chem.py
gekim/fields/chem/electro.py
gekim/fields/chem/flow.py
gekim/fields/chem/surface.py
gekim/fields/phys/__init__.py
gekim/fields/phys/photo.py
gekim/fields/phys/plasma.py
gekim/fields/phys/quantum.py
gekim/fields/phys/stat_mech.py
gekim/fields/phys/tpt.py
gekim/schemes/__init__.py
gekim/schemes/scheme.py
gekim/schemes/species.py
gekim/schemes/transition.py
gekim/simulators/__init__.py
gekim/simulators/base.py
gekim/simulators/gillespie.py
gekim/simulators/ode_solver.py
gekim/simulators/ode_solver_moddable.py
gekim/systems/__init__.py
gekim/systems/path.py
gekim/systems/system.py
gekim/utils/__init__.py
gekim/utils/experiments.py
gekim/utils/fitting.py
gekim/utils/helpers.py
gekim/utils/logging.py
gekim/utils/plotting.py
gekim-0.7.8.dist-info/licenses/LICENSE
tests/test_nstate_ode.py
gekim-0.7.8.dist-info/METADATA
gekim-0.7.8.dist-info/WHEEL
gekim-0.7.8.dist-info/top_level.txt
gekim-0.7.8.dist-info/RECORD
