Metadata-Version: 2.4
Name: gekim
Version: 0.7.8
Summary: Generalized Kinetic Modeler: A Python package for modeling arbitrary kinetic schemes.
Author-email: Kyle Ghaby <kyleghaby@gmail.com>
License-Expression: MIT
Project-URL: Homepage, https://github.com/kghaby/GeKiM
Classifier: Development Status :: 4 - Beta
Classifier: Intended Audience :: Science/Research
Classifier: Topic :: Scientific/Engineering :: Chemistry
Classifier: Programming Language :: Python :: 3.9
Requires-Python: >=3.9
License-File: LICENSE
Requires-Dist: matplotlib>=3.8
Requires-Dist: numpy>=1.26
Requires-Dist: scipy>=1.13
Requires-Dist: setuptools>=67.8
Requires-Dist: sympy>=1.12
Requires-Dist: lmfit>=1.3
Dynamic: license-file
